dummy/__init__.py
dummy/data.address
dummy/data.country
dummy/data.names
dummy/main.py
data_dummy-1.1.dist-info/METADATA
data_dummy-1.1.dist-info/WHEEL
data_dummy-1.1.dist-info/entry_points.txt
data_dummy-1.1.dist-info/top_level.txt
data_dummy-1.1.dist-info/RECORD
